docgen.py
pythonista_docgen-1.0.dist-info/WHEEL
pythonista_docgen-1.0.dist-info/METADATA
pythonista_docgen-1.0.dist-info/RECORD
