Metadata-Version: 2.1
Name: pythonista-docgen
Version: 1.0
Summary: Pythonista markdown document generator from single file docstrings
Home-page: https://github.com/mikaelho/docgen
License: TheUnlicense
Author: Mikael Honkala
Author-email: mikael.honkala@gmail.com
Classifier: Operating System :: iOS
